cnc/__init__.py
cnc/client.py
cnc/login.py
cnc/logout.py
cnc/main.py
cnc/portal.py
cnc/probe.py
cnc/keep_alive/__init__.py
cnc/keep_alive/polling.py
cnc/keep_alive/relogin.py
cnc_cli-0.1.1.dist-info/licenses/LICENSE
cnc_cli-0.1.1.dist-info/METADATA
cnc_cli-0.1.1.dist-info/WHEEL
cnc_cli-0.1.1.dist-info/entry_points.txt
cnc_cli-0.1.1.dist-info/top_level.txt
cnc_cli-0.1.1.dist-info/RECORD
