Metadata-Version: 2.4
Name: cnc-cli
Version: 0.1.1
Summary: Campus network control (cnc)
Author-email: ermengchao <zhangchao050530@gmail.com>
License-Expression: MIT
Project-URL: Homepage, https://github.com/ermengchao/cnc
Project-URL: Repository, https://github.com/ermengchao/cnc
Project-URL: Issues, https://github.com/ermengchao/cnc/issues
Classifier: Programming Language :: Python :: 3
Classifier: Programming Language :: Python :: 3.11
Classifier: Programming Language :: Python :: 3.12
Classifier: Programming Language :: Python :: 3.13
Requires-Python: >=3.11
License-File: LICENSE
Requires-Dist: requests>=2.31.0
Requires-Dist: typer>=0.9.0
Requires-Dist: rich>=13.0.0
Requires-Dist: schedule>=1.2.0
Dynamic: license-file
